{
         "error":false,
         "filename":"ctosp_hydrogen-9.0-20190417-1553-OFFICIAL.zip",
         "datetime":1555631274,
         "size":875426514,
         "url":"https://sourceforge.net/projects/ctosp/files/hydrogen/ctosp_hydrogen-9.0-20190417-1553-OFFICIAL.zip",
         "filehash":"3ca9549fb8dce43e27bd37f6e6bc815f",
         "version":"Pie",
         "id":"",
         "website_url":"https://ctosp.org",
         "news_url":"https://t.me/ctosp_feed",
         "donate_url":"https://www.paypal.me/krishvk",
         "maintainer":"vamsee krishnaa",
         "maintainer_url":"https://t.me/vamsee9",
         "forum_url":""
}
